Workbook

Sheet Summary
A1: BIONIQ TRADER — COST MODEL (at a glance)
A3: VARIABLE COST PER COACHING SESSION (AI)
A4: Model | B4: $ / session | C4: ¢ / session
A5: Opus 4.8 | B5: ='AI per Session'!D8 -> 0.075 | C5: ='AI per Session'!D9 -> 7.5
A6: Sonnet 4.6 | B6: ='AI per Session'!E8 -> 0.045 | C6: ='AI per Session'!E9 -> 4.5
A7: Haiku 4.5 | B7: ='AI per Session'!F8 -> 0.015 | C7: ='AI per Session'!F9 -> 1.5
A9: PAYMENT SKIM (Stripe)
A10: $10 charge — effective % | B10: ='Payment Skim'!D6 -> 0.059
A11: $50 charge — effective % | B11: ='Payment Skim'!D8 -> 0.035
A13: CLOUDFLARE
A14: ~$0 variable (tokens pass through at cost); cache hits free; optional ~$5/mo flat (Workers Paid).
A16: BOTTOM LINE
A17: Variable cost per session is dominated by Anthropic, not Stripe or Cloudflare —
A18: single-digit cents with the levers on (cache static context, route cheap tasks to Haiku,
A19: reserve Sonnet/Opus for coaching judgment, batch the Briefing). Set the credit price
A20: comfortably above that. The one number to respect: the ~6% payment skim on sub-$10 charges.

Sheet Assumptions
A1: BIONIQ TRADER — COST MODEL ASSUMPTIONS
A3: ANTHROPIC RATES ($ per 1M tokens)
A4: Model | B4: Input | C4: Output
A5: Opus 4.8 | B5: 5 | C5: 25
A6: Sonnet 4.6 | B6: 3 | C6: 15
A7: Haiku 4.5 | B7: 1 | C7: 5
A9: LEVERS
A10: Cache read multiplier (x input) | B10: 0.1
A11: Batch discount (x, for Briefing) | B11: 0.5
A13: PER COACHING SESSION (tokens) — edit these
A14: Cached context (dossier+strat+rubric) | B14: 20000
A15: Fresh input (trade data + request) | B15: 3000
A16: Output (coaching) | B16: 2000
A18: STRIPE
A19: Percentage | B19: 0.029
A20: Fixed fee — US ($) | B20: 0.3
A21: Fixed fee — Canada (C$) | B21: 0.3
A23: CLOUDFLARE
A24: AI Gateway variable per call (pass-through) | B24: 0
A25: Workers Paid flat ($/mo, optional) | B25: 5
A26: Unified-billing fee (optional %) | B26: 0.05

Sheet AI per Session
A1: AI COST PER COACHING SESSION
A2: Computed from Assumptions. Change token counts there; this recalculates.
A4: Component | B4: Tokens | C4: Rate basis | D4: Opus 4.8 | E4: Sonnet 4.6 | F4: Haiku 4.5
A5: Cached context read | B5: =Assumptions!B14 -> 20000 | C5: input x 0.1 | D5: =B5/1000000*Assumptions!B5*Assumptions!B10 -> 0.01 | E5: =B5/1000000*Assumptions!B6*Assumptions!B10 -> 0.006 | F5: =B5/1000000*Assumptions!B7*Assumptions!B10 -> 0.002
A6: Fresh input | B6: =Assumptions!B15 -> 3000 | C6: input | D6: =B6/1000000*Assumptions!B5 -> 0.015 | E6: =B6/1000000*Assumptions!B6 -> 0.009 | F6: =B6/1000000*Assumptions!B7 -> 0.003
A7: Output (coaching) | B7: =Assumptions!B16 -> 2000 | C7: output | D7: =B7/1000000*Assumptions!C5 -> 0.05 | E7: =B7/1000000*Assumptions!C6 -> 0.03 | F7: =B7/1000000*Assumptions!C7 -> 0.01
A8: TOTAL per session ($) | D8: =SUM(D5:D7) -> 0.075 | E8: =SUM(E5:E7) -> 0.045 | F8: =SUM(F5:F7) -> 0.015
A9: TOTAL per session (¢) | D9: =D8*100 -> 7.5 | E9: =E8*100 -> 4.5 | F9: =F8*100 -> 1.5

Sheet Payment Skim
A1: STRIPE PAYMENT SKIM (US; Canada = same % + C$0.30)
A2: The fixed 30¢ dominates small charges — the $10 toll / $9.99 journal is ~6%, not 2.9%.
A4: Charge | B4: Stripe fee | C4: Net to you | D4: Effective %
A5: 9.99 | B5: =A5*Assumptions!$B$19+Assumptions!$B$20 -> 0.58971 | C5: =A5-B5 -> 9.40029 | D5: =B5/A5 -> 0.05903003
A6: 10 | B6: =A6*Assumptions!$B$19+Assumptions!$B$20 -> 0.59 | C6: =A6-B6 -> 9.41 | D6: =B6/A6 -> 0.059
A7: 25 | B7: =A7*Assumptions!$B$19+Assumptions!$B$20 -> 1.025 | C7: =A7-B7 -> 23.975 | D7: =B7/A7 -> 0.041
A8: 50 | B8: =A8*Assumptions!$B$19+Assumptions!$B$20 -> 1.75 | C8: =A8-B8 -> 48.25 | D8: =B8/A8 -> 0.035
A9: 100 | B9: =A9*Assumptions!$B$19+Assumptions!$B$20 -> 3.2 | C9: =A9-B9 -> 96.8 | D9: =B9/A9 -> 0.032
